gato/__init__.py
gato/config.py
gato/models/__init__.py
gato/models/embedding.py
gato/models/tokenizers.py
gato/models/transformer.py
gato_tf-0.0.4.dist-info/LICENSE
gato_tf-0.0.4.dist-info/METADATA
gato_tf-0.0.4.dist-info/WHEEL
gato_tf-0.0.4.dist-info/top_level.txt
gato_tf-0.0.4.dist-info/RECORD
