Metadata-Version: 2.1
Name: gato-tf
Version: 0.0.4
Summary: Unofficial Gato: A Generalist Agent
Home-page: https://github.com/OrigamiDream/gato.git
Author: OrigamiDream
Author-email: hello@origamidream.me
License: MIT
Keywords: deep learning,gato,tensorflow,generalist agent
Classifier: Development Status :: 4 - Beta
Classifier: Intended Audience :: Developers
Classifier: Topic :: Scientific/Engineering :: Artificial Intelligence
Classifier: License :: OSI Approved :: MIT License
Classifier: Programming Language :: Python :: 3.10
Requires-Python: >=3.10.0
License-File: LICENSE
Requires-Dist: tensorflow (>=2.11)
Requires-Dist: flowchain (>=0.0.4)
